Flastel/__init__.py
Flastel/methods.py
Flatel-0.0.3.dist-info/LICENSE
Flatel-0.0.3.dist-info/METADATA
Flatel-0.0.3.dist-info/WHEEL
Flatel-0.0.3.dist-info/top_level.txt
Flatel-0.0.3.dist-info/RECORD
