Metadata-Version: 2.1
Name: Flatel
Version: 0.0.3
Summary: Flastel – Telegram Bot API.
Home-page: https://github.com/DepyXa/Flastel
Author: DepyXa
Author-email: dere96632@gmail.com
Project-URL: GitHub, https://github.com/DepyXa/Flastel
Keywords: Telegram Bot API bot python
Requires-Python: >=3.6
License-File: LICENSE
Requires-Dist: requests >=2.25.1
Requires-Dist: aiohttp >=3.8.6
